gitag/auto_tagger.py
gitag/changelog_writer.py
gitag/config.py
gitag/config_validator.py
gitag/git_repo.py
gitag/main.py
gitag/version_manager.py
gitag/utils/__init__.py
gitag/utils/logging_setup.py
gitag-1.0.8.dist-info/licenses/LICENSE
gitag-1.0.8.dist-info/METADATA
gitag-1.0.8.dist-info/WHEEL
gitag-1.0.8.dist-info/entry_points.txt
gitag-1.0.8.dist-info/top_level.txt
gitag-1.0.8.dist-info/RECORD
