Metadata-Version: 2.4
Name: gitag
Version: 1.0.8
Summary: A CLI tool for automatic git tagging based on commit messages
Author-email: Henry Manke <info@hm-co.de>
License-Expression: MIT
Project-URL: Homepage, https://github.com/henrymanke/gitag
Project-URL: Issues, https://github.com/henrymanke/gitag/issues
Classifier: Programming Language :: Python :: 3
Classifier: Programming Language :: Python :: 3.11
Classifier: Operating System :: OS Independent
Classifier: Topic :: Software Development :: Version Control :: Git
Classifier: Intended Audience :: Developers
Requires-Python: >=3.11
License-File: LICENSE
Provides-Extra: dev
Requires-Dist: pytest>=8.0; extra == "dev"
Requires-Dist: pytest-mock; extra == "dev"
Requires-Dist: coverage; extra == "dev"
Requires-Dist: build; extra == "dev"
Requires-Dist: twine; extra == "dev"
Dynamic: license-file
